kryptikkaocutils/Input.py
kryptikkaocutils/Timer.py
kryptikkaocutils/__init__.py
kryptikkaocutils-0.0.3.dist-info/METADATA
kryptikkaocutils-0.0.3.dist-info/WHEEL
kryptikkaocutils-0.0.3.dist-info/top_level.txt
kryptikkaocutils-0.0.3.dist-info/RECORD
